[
  {
    "name": "Murata",
    "population": 0,
    "country": "Saint-Marin",
    "state": "San Marino",
    "populationName": ""
  },
  {
    "name": "Santa Mustiola",
    "population": 0,
    "country": "Saint-Marin",
    "state": "San Marino",
    "populationName": ""
  },
  {
    "name": "Casole",
    "population": 0,
    "country": "Saint-Marin",
    "state": "San Marino",
    "populationName": ""
  },
  {
    "name": "Gualdicciolo",
    "population": 0,
    "country": "Saint-Marin",
    "state": "Acquaviva",
    "populationName": ""
  },
  {
    "name": "Cà Rigo",
    "population": 0,
    "country": "Saint-Marin",
    "state": "Borgo Maggiore",
    "populationName": ""
  },
  {
    "name": "Piandivello",
    "population": 0,
    "country": "Saint-Marin",
    "state": "Domagnano",
    "populationName": ""
  },
  {
    "name": "Cerbaiola",
    "population": 0,
    "country": "Saint-Marin",
    "state": "Montegiardino",
    "populationName": ""
  },
  {
    "name": "Falciano",
    "population": 1000,
    "country": "Saint-Marin",
    "state": "Serravalle",
    "populationName": ""
  },
  {
    "name": "Dogana",
    "population": 0,
    "country": "Saint-Marin",
    "state": "Serravalle",
    "populationName": ""
  },
  {
    "name": "Fiorina",
    "population": 0,
    "country": "Saint-Marin",
    "state": "Serravalle",
    "populationName": ""
  }
]